[
  {
    "question": "Выберите пятерку треф. Запомните её.",
    "options": [
      {
        "img": "/path/to/карта1.png",
        "alt": "Карта 1 (например, семерка бубен)"
      },
      {
        "img": "/path/to/карта2.png",
        "alt": "Карта 2 (например, десятка червей)"
      },
      {
        "img": "/path/to/карта3.png",
        "alt": "Карта 3 (например, валет пик)"
      },
      { "img": "/path/to/пятерка_треф.png", "alt": "Пятерка треф" }
    ],
    "correctAnswer": 3
  },
  {
    "question": "Выберите пятерку треф, которую вы запомнили на прошлом вопросе.",
    "options": [
      {
        "img": "/path/to/карта4.png",
        "alt": "Карта 4 (например, король крестей)"
      },
      { "img": "/path/to/пятерка_треф.png", "alt": "Пятерка треф" },
      { "img": "/path/to/карта6.png", "alt": "Карта 6 (например, дама пик)" },
      {
        "img": "/path/to/карта7.png",
        "alt": "Карта 7 (например, туз червей)"
      }
    ],
    "correctAnswer": 1
  },
  {
    "question": "<Запомните эту фигуру. Выберите такую же на следующем вопросе.",
    "options": [
      { "img": "/path/to/синий_квадрат.png", "alt": "Синий квадрат" },
      { "img": "/path/to/зеленый_круг.png", "alt": "Зеленый круг" },
      {
        "img": "/path/to/красный_треугольник.png",
        "alt": "Красный треугольник"
      },
      {
        "img": "/path/to/желтый_прямоугольник.png",
        "alt": "Желтый прямоугольник"
      }
    ],
    "correctAnswer": 2
  },
  {
    "question": "Выберите красный треугольник.",
    "options": [
      {
        "img": "/path/to/желтый_прямоугольник.png",
        "alt": "Желтый прямоугольник"
      },
      {
        "img": "/path/to/красный_треугольник.png",
        "alt": "Красный треугольник"
      },
      { "img": "/path/to/синий_квадрат.png", "alt": "Синий квадрат" },
      { "img": "/path/to/зеленый_круг.png", "alt": "Зеленый круг" }
    ],
    "correctAnswer": 1
  },
  {
    "question": "<Запомните это лицо. Выберите такое же на следующем вопросе.",
    "options": [
      { "img": "/path/to/лицо2.jpg", "alt": "Лицо 2" },
      { "img": "/path/to/лицо3.jpg", "alt": "Лицо 3" },
      { "img": "/path/to/лицо1.jpg", "alt": "Лицо 1" },
      { "img": "/path/to/лицо4.jpg", "alt": "Лицо 4" }
    ],
    "correctAnswer": 2
  },
  {
    "question": "Выберите то же лицо.",
    "options": [
      { "img": "/path/to/лицо4.jpg", "alt": "Лицо 4" },
      { "img": "/path/to/лицо1.jpg", "alt": "Лицо 1" },
      { "img": "/path/to/лицо2.jpg", "alt": "Лицо 2" },
      { "img": "/path/to/лицо3.jpg", "alt": "Лицо 3" }
    ],
    "correctAnswer": 1
  },
  {
    "question": "Запомните это изображение. Выберите такое же на следующем вопросе.",
    "options": [
      {
        "img": "/path/to/абстрактное2.png",
        "alt": "Абстрактное изображение 2"
      },
      {
        "img": "/path/to/абстрактное1.png",
        "alt": "Абстрактное изображение 1"
      },
      {
        "img": "/path/to/абстрактное3.png",
        "alt": "Абстрактное изображение 3"
      },
      {
        "img": "/path/to/абстрактное4.png",
        "alt": "Абстрактное изображение 4"
      }
    ],
    "correctAnswer": 1
  },
  {
    "question": "Выберите то же абстрактное изображение.",
    "options": [
      {
        "img": "/path/to/абстрактное3.png",
        "alt": "Абстрактное изображение 3"
      },
      {
        "img": "/path/to/абстрактное4.png",
        "alt": "Абстрактное изображение 4"
      },
      {
        "img": "/path/to/абстрактное1.png",
        "alt": "Абстрактное изображение 1"
      },
      {
        "img": "/path/to/абстрактное2.png",
        "alt": "Абстрактное изображение 2"
      }
    ],
    "correctAnswer": 2
  },
  {
    "question": "Запомните слово \"ЯБЛОКО\". Выберите \"ЯБЛОКО\" на следующем вопросе.",
    "options": ["АПЕЛЬСИН", "ЯБЛОКО", "БАНАН", "ВИНОГРАД"],
    "correctAnswer": 1
  },
  {
    "question": "Выберите \"ЯБЛОКО\".",
    "options": ["БАНАН", "ВИНОГРАД", "ЯБЛОКО", "АПЕЛЬСИН"],
    "correctAnswer": 2
  }
]
